qread/__init__.py
qread/__main__.py
qread/_version.py
qread/py.typed
qread-1.0.0.dist-info/LICENSE
qread-1.0.0.dist-info/METADATA
qread-1.0.0.dist-info/WHEEL
qread-1.0.0.dist-info/entry_points.txt
qread-1.0.0.dist-info/top_level.txt
qread-1.0.0.dist-info/RECORD
