Metadata-Version: 2.1
Name: qread
Version: 1.0.0
Summary: Read a QR code from an image file.
Author-email: Ryan Kozak <ReK42@users.noreply.github.com>
Maintainer-email: Ryan Kozak <ReK42@users.noreply.github.com>
License: GNU GENERAL PUBLIC LICENSE
Project-URL: Repository, https://github.com/ReK42/qread
Project-URL: Issues, https://github.com/ReK42/qread/issues
Classifier: Development Status :: 5 - Production/Stable
Classifier: Environment :: Console
Classifier: Intended Audience :: End Users/Desktop
Classifier: License :: OSI Approved :: GNU General Public License v3 (GPLv3)
Classifier: Natural Language :: English
Classifier: Operating System :: OS Independent
Classifier: Programming Language :: Python
Classifier: Programming Language :: Python :: 3
Classifier: Programming Language :: Python :: 3 :: Only
Classifier: Programming Language :: Python :: 3.9
Classifier: Programming Language :: Python :: 3.10
Classifier: Programming Language :: Python :: 3.11
Classifier: Programming Language :: Python :: 3.12
Classifier: Topic :: Utilities
Classifier: Typing :: Typed
Requires-Python: >=3.9
License-File: LICENSE
Requires-Dist: opencv-python ==4.10.0.84
Provides-Extra: build
Requires-Dist: setuptools ==72.1.0 ; extra == 'build'
Requires-Dist: setuptools-scm ==8.1.0 ; extra == 'build'
Requires-Dist: build ==1.2.1 ; extra == 'build'
Requires-Dist: twine ==5.1.1 ; extra == 'build'
Provides-Extra: test
Requires-Dist: mypy ==1.11.1 ; extra == 'test'
Requires-Dist: ruff ==0.5.6 ; extra == 'test'
